AUTHORS
COPYING
NEWS.md
README.md
docs/Makefile
docs/bezier.rst
docs/conf.py
docs/documentation.rst
docs/how-it-works.rst
docs/index.rst
docs/make.bat
docs/tutorial.rst
ip-link/D3js/index.html
ip-link/__init__.py
ip-link/bezier/example.sh
ip-link/bezier/object_to_image.py
ip-link/bezier/pcap_to_sqlite.py
ip-link/bezier/sqlite_to_object.py
ip-link/circos_to_data.py
ip-link/csv_to_graphviz.py
ip-link/csv_to_histogram.py
ip-link/csv_to_piechart.py
ip-link/moowheel/canvastext.js
ip-link/moowheel/excanvas.js
ip-link/moowheel/mootools-1.2-core-nc.js
ip-link/moowheel/mootools-1.2-more.js
ip-link/moowheel/moowheel.js
ip-link/object_to_GvGen.py
ip-link/object_to_circos.py
ip-link/object_to_csv.py
ip-link/object_to_d3js_matrix.py
ip-link/object_to_gexf.py
ip-link/object_to_graph.py
ip-link/object_to_graphviz.py
ip-link/object_to_html.py
ip-link/object_to_moowheel.py
ip-link/object_to_rtgraph.py
ip-link/object_to_scatterplot.py
ip-link/object_to_xml.py
ip-link/pcap_to_object.py
ip-link/pcap_to_sqlite.py
ip-link/pcap_to_sqlite.sh
ip-link/rtgraph3d/__init__.py
ip-link/rtgraph3d/hydra.py
ip-link/rtgraph3d/povexport.py
ip-link/rtgraph3d/rtg/c60.rtg
ip-link/rtgraph3d/rtg/hexadeca.rtg
ip-link/rtgraph3d/rtg_cli.py
ip-link/rtgraph3d/rtgraph3d.py
ip-link/scatterplot/cat.inc
ip-link/scatterplot/data.inc
ip-link/scatterplot/index.html
ip-link/scatterplot/scatterplot
ip-link/scatterplot/scatterplot.png
ip-link/sqlite_to_object.py
ip-link/sqlite_to_picviz.py
ip-link/xml_to_histogram.py
ip_link-0.4.1.dist-info/COPYING
ip_link-0.4.1.dist-info/WHEEL
ip_link-0.4.1.dist-info/METADATA
ip_link-0.4.1.dist-info/RECORD
