Metadata-Version: 2.1
Name: ip-link
Version: 0.4.1
Summary: Visualizing the relationships between different IP from network traffic capture.
Home-page: https://sr.ht/~cedric/ip-link
License: GPL-3.0-or-later
Author: Cédric Bonhomme
Author-email: cedric@cedricbonhomme.org
Requires-Python: >=3.8,<4.0
Classifier: Development Status :: 5 - Production/Stable
Classifier: Environment :: Console
Classifier: Intended Audience :: Developers
Classifier: Intended Audience :: Science/Research
Classifier: License :: OSI Approved :: GNU General Public License v3 or later (GPLv3+)
Classifier: Operating System :: OS Independent
Classifier: Programming Language :: Python :: 3
Classifier: Programming Language :: Python :: 3.10
Classifier: Programming Language :: Python :: 3.8
Classifier: Programming Language :: Python :: 3.9
Classifier: Topic :: Security
Requires-Dist: Pillow (>=9.0.0,<10.0.0)
Requires-Dist: matplotlib (>=3.5.1,<4.0.0)
Requires-Dist: networkx (>=2.6.3,<3.0.0)
Requires-Dist: numpy (>=1.22.1,<2.0.0)
Requires-Dist: pypacker (>=5.1,<6.0)
Project-URL: Repository, https://git.sr.ht/~cedric/ip-link
